cli/__init__.py
cli/__version__.py
cli/config.json
cli/constants.py
cli/database.py
cli/utils.py
cli/wowtool.py
cli/commands/__init__.py
cli/commands/configure.py
cli/commands/live.py
cli/commands/livestream.py
cli/commands/mapping.py
cli/commands/recording.py
cli/commands/resource.py
cli/commands/transcoder.py
tests/__init__.py
tests/test_cli.py
tests/test_database.py
tests/test_utils.py
wowtool-0.1.33.dist-info/LICENSE
wowtool-0.1.33.dist-info/METADATA
wowtool-0.1.33.dist-info/WHEEL
wowtool-0.1.33.dist-info/entry_points.txt
wowtool-0.1.33.dist-info/top_level.txt
wowtool-0.1.33.dist-info/RECORD
